{
  "id": 37025766,
  "type": "resume",
  "renderingToken": "HVbasWh69Wdcg98vBs3rkgV6",
  "name": null,
  "avatar": {
    "transform": {
      "rect": {
        "x": 0,
        "y": 0.006003430531732357,
        "width": 1,
        "height": 0.9879931389365353
      },
      "zoom": 1,
      "angle": 0,
      "customBackground": {
        "color": null,
        "image": null
      }
    },
    "largeUrl": "https://s3.resume.io/uploads/profile_picture/file/13026097/8242a74cd3ad4a58637f4281a84bc7ea.jpg?version=477f595aa",
    "thumbUrl": "https://s3.resume.io/uploads/profile_picture/file/13026097/thumb_8242a74cd3ad4a58637f4281a84bc7ea.jpg?version=477f595aa",
    "mediumUrl": "https://s3.resume.io/uploads/profile_picture/file/13026097/medium_squared_8242a74cd3ad4a58637f4281a84bc7ea.jpg?version=477f595aa",
    "originalUrl": "https://s3.resume.io/uploads/profile_picture/original_file/13026097/9b6708c6800f8c18b09abeb543660c20.jpg",
    "blank": false
  },
  "position": "Full Stack Developer",
  "firstName": "Ronald",
  "lastName": "Adriansyah",
  "phoneNumber": "087889896874",
  "countryName": "Indonesia",
  "city": "Tangerang",
  "address": null,
  "postalCode": null,
  "birthPlace": null,
  "birthDate": null,
  "drivingLicense": null,
  "nationality": null,
  "email": "sschouse@gmail.com",
  "profile": "A professional with more than 15 years of relevant work experience in Web Developer,Fullstack & Desktop Programmer,Ialso make website more & more interactive",
  "template": "new_york",
  "sectionsOrder": [
    "profile",
    "workExperiences",
    "educations",
    "socialProfiles",
    "skills",
    "courses",
    "languages"
  ],
  "color": null,
  "spacing": 0,
  "version": "efdf686481",
  "secureId": null,
  "locale": "en",
  "gender": null,
  "namePronunciation": null,
  "addressPronunciation": null,
  "resumeSubmissionDate": null,
  "married": false,
  "numberOfDependents": null,
  "spouseObligation": false,
  "commutingTime": null,
  "spaceForPersonalRequests": null,
  "referencesUponRequest": null,
  "hideSkillLevel": false,
  "sectionTitles": {},
  "showPrefillResumeModal": false,
  "motivation": null,
  "pr": null,
  "qualifications": null,
  "technicalSkills": null,
  "skillsDescription": null,
  "employerName": null,
  "jobTitle": null,
  "linkedin": null,
  "jobPostingHostName": null,
  "updatedAt": "2023-11-29T10:04:22+01:00",
  "createdAt": "2023-11-29T08:31:26+01:00",
  "workExperiences": [
    {
      "id": 68492768,
      "title": "Full stack Developer",
      "employer": "PT. Edrus Digital Strategy",
      "city": "Metland Tangerang, Jl. Puri Utama No.7, Kec. Cipondoh, Kota Tangerang",
      "dateFrom": "2021-01-01",
      "dateUntil": null,
      "description": "Full stack Developer",
      "resumeId": 37025766,
      "position": 1,
      "isMonthUntilHidden": false,
      "isDateUntilPresent": true,
      "isMonthFromHidden": false,
      "normalizedJobTitleId": 615,
      "reasonForResignation": null,
      "plannedResignationDate": null,
      "duration": 35,
      "department": null,
      "employmentType": null,
      "employerProfilesAttributes": {
        "id": 14785429,
        "businessType": null,
        "foundationYear": null,
        "capital": null,
        "sales": null,
        "noOfEmployee": null,
        "stockListing": null,
        "resumeWorkExperienceId": 68492768,
        "position": null
      },
      "cid": null
    },
    {
      "id": 68492872,
      "title": "Full stack Developer",
      "employer": "PT. Proteksi Antar Nusa",
      "city": "Gandaria 8 Tower , Jakarta Selatan",
      "dateFrom": "2019-11-01",
      "dateUntil": "2020-09-01",
      "description": "Work with IT Director to develop large, complex web service for Restful API projects for Bank Syariah Mandiri.Develop N.B.I.S Management and maintain optimal workflow.",
      "resumeId": 37025766,
      "position": 2,
      "isMonthUntilHidden": false,
      "isDateUntilPresent": false,
      "isMonthFromHidden": false,
      "normalizedJobTitleId": 615,
      "reasonForResignation": null,
      "plannedResignationDate": null,
      "duration": 10,
      "department": null,
      "employmentType": null,
      "employerProfilesAttributes": {
        "id": 14785540,
        "businessType": null,
        "foundationYear": null,
        "capital": null,
        "sales": null,
        "noOfEmployee": null,
        "stockListing": null,
        "resumeWorkExperienceId": 68492872,
        "position": null
      },
      "cid": null
    },
    {
      "id": 68492980,
      "title": "Desktop,Web Programmer",
      "employer": "PT. Ridia Akusa Utama Holding Company",
      "city": "Serpong ,Tangerang",
      "dateFrom": "2018-08-01",
      "dateUntil": "2019-08-01",
      "description": "Develop R.A.U Integrated Information System(Accounting,modul,Sales,Stock and Purchase Modul).Working closely with the business leaders of other units in giving advice,recommendations on the future work plan and the development of technological resources such as hardware,infrastructure,telecommunications,and others. Designing,managing and monitoring as well as the evaluation of the operation of information systems (software and applications) and supporting (hardware,infrastructure,telecommunications).",
      "resumeId": 37025766,
      "position": 3,
      "isMonthUntilHidden": false,
      "isDateUntilPresent": false,
      "isMonthFromHidden": false,
      "normalizedJobTitleId": 3230279,
      "reasonForResignation": null,
      "plannedResignationDate": null,
      "duration": 12,
      "department": null,
      "employmentType": null,
      "employerProfilesAttributes": {
        "id": 14785688,
        "businessType": null,
        "foundationYear": null,
        "capital": null,
        "sales": null,
        "noOfEmployee": null,
        "stockListing": null,
        "resumeWorkExperienceId": 68492980,
        "position": null
      },
      "cid": null
    },
    {
      "id": 68493103,
      "title": "Full stack Developer, Desktop Programmer",
      "employer": "PT. Sinar Rezeki Handal(indogold.id)",
      "city": "Daan Mogot KM.22 Tangerang",
      "dateFrom": "2009-06-01",
      "dateUntil": "2018-05-01",
      "description": "Develop Integrated Information System(Accounting modul,Sales,Stock and Purchase modul,etc).Create a Company Logo.Build a Website for Company Profil.Develop Point Of Sales and GPS Tracking Mobile App.Working closely with the owner in giving advice,recommendations on the future work plan and the development of technological resources such as hardware,infrastructure,telecommunications,and others.Designing,managing and monitoring as well as the evaluation of the operation of information systems (software and applications) and supporting (hardware,infrastructure,telecommunications).",
      "resumeId": 37025766,
      "position": 4,
      "isMonthUntilHidden": false,
      "isDateUntilPresent": false,
      "isMonthFromHidden": false,
      "normalizedJobTitleId": 3230280,
      "reasonForResignation": null,
      "plannedResignationDate": null,
      "duration": 108,
      "department": null,
      "employmentType": null,
      "employerProfilesAttributes": {
        "id": 14785849,
        "businessType": null,
        "foundationYear": null,
        "capital": null,
        "sales": null,
        "noOfEmployee": null,
        "stockListing": null,
        "resumeWorkExperienceId": 68493103,
        "position": null
      },
      "cid": null
    },
    {
      "id": 68493237,
      "title": "Programmer",
      "employer": "PT. Rasico Industry LTD",
      "city": "Daan Mogot Tangerang",
      "dateFrom": "2007-05-01",
      "dateUntil": "2009-06-01",
      "description": "Build E.R.P System with a team.",
      "resumeId": 37025766,
      "position": 5,
      "isMonthUntilHidden": false,
      "isDateUntilPresent": false,
      "isMonthFromHidden": false,
      "normalizedJobTitleId": 34,
      "reasonForResignation": null,
      "plannedResignationDate": null,
      "duration": 25,
      "department": null,
      "employmentType": null,
      "employerProfilesAttributes": {
        "id": 14786028,
        "businessType": null,
        "foundationYear": null,
        "capital": null,
        "sales": null,
        "noOfEmployee": null,
        "stockListing": null,
        "resumeWorkExperienceId": 68493237,
        "position": null
      },
      "cid": null
    },
    {
      "id": 68493309,
      "title": "Hardware & Software Support (M.I.S)",
      "employer": "PT. Ciputra Residence",
      "city": "Citra Raya,tiga raksa Tangerang",
      "dateFrom": "1997-01-01",
      "dateUntil": "1998-08-01",
      "description": "Create Database for sales property and information of &nbsp;customer by using MAPINFO software application.",
      "resumeId": 37025766,
      "position": 6,
      "isMonthUntilHidden": false,
      "isDateUntilPresent": false,
      "isMonthFromHidden": false,
      "normalizedJobTitleId": 3230281,
      "reasonForResignation": null,
      "plannedResignationDate": null,
      "duration": 19,
      "department": null,
      "employmentType": null,
      "employerProfilesAttributes": {
        "id": 14786120,
        "businessType": null,
        "foundationYear": null,
        "capital": null,
        "sales": null,
        "noOfEmployee": null,
        "stockListing": null,
        "resumeWorkExperienceId": 68493309,
        "position": null
      },
      "cid": null
    }
  ],
  "educations": [
    {
      "id": 48368179,
      "school": "Budi Luhur University",
      "degree": "Bachelor Degree(S1)",
      "level": null,
      "city": "Petukangan Utara, Kec. Pesanggrahan, Kota Jakarta Selatan, Daerah Khusus Ibukota Jakarta",
      "dateFrom": "2016-06-01",
      "dateUntil": null,
      "description": null,
      "resumeId": 37025766,
      "createdAt": "2023-11-29T08:48:39.435+01:00",
      "updatedAt": "2023-11-29T08:49:46.399+01:00",
      "position": 1,
      "isMonthUntilHidden": false,
      "isDateUntilPresent": true,
      "isMonthFromHidden": false,
      "faculty": null,
      "department": null,
      "cid": null
    }
  ],
  "courses": [
    {
      "id": 19961590,
      "course": "ERP Planning,Teamwork and Communication,and Business Report Analytics",
      "institution": "MonSoon Academy",
      "dateFrom": "2019-09-01",
      "dateUntil": "2019-10-01",
      "description": null,
      "resumeId": 37025766,
      "createdAt": "2023-11-29T08:52:34.714+01:00",
      "updatedAt": "2023-11-29T08:53:30.288+01:00",
      "position": 1,
      "isMonthUntilHidden": false,
      "isDateUntilPresent": false,
      "isMonthFromHidden": false,
      "cid": null
    }
  ],
  "internships": [],
  "activities": [],
  "skills": [
    {
      "id": 152514005,
      "skill": "Microsoft Excel",
      "level": "expert",
      "resumeId": 37025766,
      "createdAt": "2023-11-29T08:52:11.432+01:00",
      "updatedAt": "2023-11-29T08:52:11.432+01:00",
      "position": 1,
      "sourceAlgo": null,
      "skillType": null,
      "details": null,
      "cid": null
    },
    {
      "id": 152514004,
      "skill": "Microsoft PowerPoint",
      "level": "expert",
      "resumeId": 37025766,
      "createdAt": "2023-11-29T08:52:10.441+01:00",
      "updatedAt": "2023-11-29T08:52:11.443+01:00",
      "position": 2,
      "sourceAlgo": null,
      "skillType": null,
      "details": null,
      "cid": null
    },
    {
      "id": 152514000,
      "skill": "Docker",
      "level": "expert",
      "resumeId": 37025766,
      "createdAt": "2023-11-29T08:52:05.866+01:00",
      "updatedAt": "2023-11-29T08:52:11.449+01:00",
      "position": 3,
      "sourceAlgo": null,
      "skillType": null,
      "details": null,
      "cid": null
    },
    {
      "id": 152513996,
      "skill": "Microsoft Office",
      "level": "expert",
      "resumeId": 37025766,
      "createdAt": "2023-11-29T08:52:04.303+01:00",
      "updatedAt": "2023-11-29T08:52:11.454+01:00",
      "position": 4,
      "sourceAlgo": null,
      "skillType": null,
      "details": null,
      "cid": null
    },
    {
      "id": 152513961,
      "skill": "MySQL",
      "level": "expert",
      "resumeId": 37025766,
      "createdAt": "2023-11-29T08:52:00.228+01:00",
      "updatedAt": "2023-11-29T08:52:11.460+01:00",
      "position": 5,
      "sourceAlgo": null,
      "skillType": null,
      "details": null,
      "cid": null
    },
    {
      "id": 152513938,
      "skill": "HTML & CSS",
      "level": "expert",
      "resumeId": 37025766,
      "createdAt": "2023-11-29T08:51:59.343+01:00",
      "updatedAt": "2023-11-29T08:52:11.466+01:00",
      "position": 6,
      "sourceAlgo": null,
      "skillType": null,
      "details": null,
      "cid": null
    },
    {
      "id": 152513935,
      "skill": "Git",
      "level": "expert",
      "resumeId": 37025766,
      "createdAt": "2023-11-29T08:51:58.458+01:00",
      "updatedAt": "2023-11-29T08:52:11.471+01:00",
      "position": 7,
      "sourceAlgo": null,
      "skillType": null,
      "details": null,
      "cid": null
    },
    {
      "id": 152513931,
      "skill": "MongoDB",
      "level": "expert",
      "resumeId": 37025766,
      "createdAt": "2023-11-29T08:51:53.208+01:00",
      "updatedAt": "2023-11-29T08:52:11.476+01:00",
      "position": 8,
      "sourceAlgo": null,
      "skillType": null,
      "details": null,
      "cid": null
    },
    {
      "id": 152513924,
      "skill": "Python",
      "level": "expert",
      "resumeId": 37025766,
      "createdAt": "2023-11-29T08:51:51.628+01:00",
      "updatedAt": "2023-11-29T08:52:11.482+01:00",
      "position": 9,
      "sourceAlgo": null,
      "skillType": null,
      "details": null,
      "cid": null
    },
    {
      "id": 152513925,
      "skill": "React",
      "level": "expert",
      "resumeId": 37025766,
      "createdAt": "2023-11-29T08:51:51.631+01:00",
      "updatedAt": "2023-11-29T08:52:11.487+01:00",
      "position": 10,
      "sourceAlgo": null,
      "skillType": null,
      "details": null,
      "cid": null
    },
    {
      "id": 152513926,
      "skill": "Java",
      "level": "expert",
      "resumeId": 37025766,
      "createdAt": "2023-11-29T08:51:51.634+01:00",
      "updatedAt": "2023-11-29T08:52:11.492+01:00",
      "position": 11,
      "sourceAlgo": null,
      "skillType": null,
      "details": null,
      "cid": null
    },
    {
      "id": 152513927,
      "skill": "PHP",
      "level": "expert",
      "resumeId": 37025766,
      "createdAt": "2023-11-29T08:51:51.637+01:00",
      "updatedAt": "2023-11-29T08:52:11.496+01:00",
      "position": 12,
      "sourceAlgo": null,
      "skillType": null,
      "details": null,
      "cid": null
    },
    {
      "id": 152513928,
      "skill": "SQL",
      "level": "expert",
      "resumeId": 37025766,
      "createdAt": "2023-11-29T08:51:51.639+01:00",
      "updatedAt": "2023-11-29T08:52:11.501+01:00",
      "position": 13,
      "sourceAlgo": null,
      "skillType": null,
      "details": null,
      "cid": null
    },
    {
      "id": 152513906,
      "skill": "Node.js",
      "level": "expert",
      "resumeId": 37025766,
      "createdAt": "2023-11-29T08:51:48.201+01:00",
      "updatedAt": "2023-11-29T08:52:11.506+01:00",
      "position": 14,
      "sourceAlgo": null,
      "skillType": null,
      "details": null,
      "cid": null
    },
    {
      "id": 152513904,
      "skill": "JavaScript",
      "level": "expert",
      "resumeId": 37025766,
      "createdAt": "2023-11-29T08:51:47.200+01:00",
      "updatedAt": "2023-11-29T08:52:11.511+01:00",
      "position": 15,
      "sourceAlgo": null,
      "skillType": null,
      "details": null,
      "cid": null
    },
    {
      "id": 152514307,
      "skill": "Google Cloud Platform",
      "level": "expert",
      "resumeId": 37025766,
      "createdAt": "2023-11-29T08:53:42.622+01:00",
      "updatedAt": "2023-11-29T08:54:35.994+01:00",
      "position": 16,
      "sourceAlgo": null,
      "skillType": null,
      "details": null,
      "cid": null
    }
  ],
  "languages": [],
  "hobbies": [],
  "references": [],
  "socialProfiles": [
    {
      "id": 10442503,
      "label": "Linkedin",
      "link": "http://linkedin.com/in/Ronald-adriansyah-5279073b",
      "resumeId": 37025766,
      "createdAt": "2023-11-29T08:50:08.025+01:00",
      "updatedAt": "2023-11-29T08:50:37.344+01:00",
      "position": 1,
      "cid": null
    },
    {
      "id": 10442506,
      "label": "Github",
      "link": "https://github.com/ronaldAdd",
      "resumeId": 37025766,
      "createdAt": "2023-11-29T08:50:37.874+01:00",
      "updatedAt": "2023-11-29T08:51:43.579+01:00",
      "position": 2,
      "cid": null
    }
  ],
  "customSections": []
}
